rag4p/__init__.py
rag4p/app_complete_local.py
rag4p/app_complete_weaviate.py
rag4p/app_generation_answer_bedrock.py
rag4p/app_generation_answer_generator.py
rag4p/app_generation_answer_quality.py
rag4p/app_generation_answer_quality_ollama.py
rag4p/app_generation_question_generator.py
rag4p/app_generation_questions_generator_vasa.py
rag4p/app_indexing_chain_retrieval_local.py
rag4p/app_indexing_local.py
rag4p/app_indexing_opensearch.py
rag4p/app_indexing_semantic_openai.py
rag4p/app_indexing_weaviate.py
rag4p/app_retrieval_quality_vasa.py
rag4p/app_retrieval_retriever_local.py
rag4p/app_retrieval_retriever_opensearch.py
rag4p/app_retrieval_retriever_weaviate.py
rag4p/app_retrieval_strategy.py
rag4p/app_weaviate_info.py
rag4p/indexing/__init__.py
rag4p/indexing/content_reader.py
rag4p/indexing/indexing_response.py
rag4p/indexing/indexing_service.py
rag4p/indexing/input_document.py
rag4p/indexing/jsonl_content_reader.py
rag4p/indexing/splitter.py
rag4p/indexing/splitter_chain.py
rag4p/indexing/splitters/__init__.py
rag4p/indexing/splitters/max_token_splitter.py
rag4p/indexing/splitters/section_splitter.py
rag4p/indexing/splitters/semantic_splitter.py
rag4p/indexing/splitters/sentence_splitter.py
rag4p/indexing/splitters/single_chunk_splitter.py
rag4p/integrations/__init__.py
rag4p/integrations/bedrock/__init__.py
rag4p/integrations/bedrock/access_bedrock.py
rag4p/integrations/bedrock/bedrock_answer_generator.py
rag4p/integrations/bedrock/bedrock_embedder.py
rag4p/integrations/bedrock/quality/__init__.py
rag4p/integrations/bedrock/quality/bedrock_answer_quality_service.py
rag4p/integrations/ollama/__init__.py
rag4p/integrations/ollama/access_ollama.py
rag4p/integrations/ollama/ollama_answer_generator.py
rag4p/integrations/ollama/ollama_embedder.py
rag4p/integrations/ollama/ollama_knowledge_extractor.py
rag4p/integrations/ollama/ollama_question_generator.py
rag4p/integrations/ollama/ollama_tokenizer.py
rag4p/integrations/ollama/quality/__init__.py
rag4p-0.13.3.dist-info/METADATA
rag4p-0.13.3.dist-info/WHEEL
rag4p-0.13.3.dist-info/entry_points.txt
rag4p-0.13.3.dist-info/RECORD
