Metadata-Version: 2.3
Name: rag4p
Version: 0.13.3
Summary: This project I use a lot for workshops, it contains some utils for splitters, tokenizers, and a weaviate client that I reuse a lot
Author: Jettro Coenradie
Author-email: jettro.coenradie@gmail.com
Requires-Python: >=3.12,<4.0
Classifier: Programming Language :: Python :: 3
Classifier: Programming Language :: Python :: 3.12
Classifier: Programming Language :: Python :: 3.13
Requires-Dist: boto3 (>=1.36.24,<1.37.0)
Requires-Dist: configparser (==7.1.0)
Requires-Dist: nltk (==3.9.1)
Requires-Dist: openai (>=1.63.2,<2.0.0)
Requires-Dist: opensearch-py (>=2.8.0,<2.9.0)
Requires-Dist: pandas (==2.2.3)
Requires-Dist: pycryptodome (==3.21.0)
Requires-Dist: python-dotenv (==1.0.1)
Requires-Dist: requests (==2.32.3)
Requires-Dist: requests-aws4auth (==1.3.1)
Requires-Dist: scipy (==1.14.1)
Requires-Dist: tiktoken (>=0.9.0,<1.0.0)
Requires-Dist: tokenizers (==0.20.3)
Requires-Dist: unidecode (==1.3.8)
Requires-Dist: weaviate-client (>=4.11.0,<5.0.0)
